unimpeded/__init__.py
unimpeded/_version.py
unimpeded/database.py
unimpeded-0.2.7.dist-info/licenses/LICENSE
unimpeded-0.2.7.dist-info/METADATA
unimpeded-0.2.7.dist-info/WHEEL
unimpeded-0.2.7.dist-info/top_level.txt
unimpeded-0.2.7.dist-info/RECORD
