Metadata-Version: 2.4
Name: unimpeded
Version: 0.2.7
Summary: Universal model comparison & parameter estimation over diverse datasets
Author-email: Will Handley <williamjameshandley@gmail.com>
License: MIT License
Project-URL: Homepage, https://github.com/handley-lab/unimpeded
Project-URL: Bug Tracker, https://github.com/handley-lab/unimpeded/issues
Project-URL: Documentation, https://unimpeded.readthedocs.io/en/latest/
Classifier: Programming Language :: Python :: 3
Classifier: License :: OSI Approved :: MIT License
Classifier: Operating System :: OS Independent
Classifier: Development Status :: 1 - Planning
Classifier: Intended Audience :: Developers
Classifier: Intended Audience :: Science/Research
Classifier: Natural Language :: English
Classifier: Topic :: Scientific/Engineering
Classifier: Topic :: Scientific/Engineering :: Astronomy
Classifier: Topic :: Scientific/Engineering :: Physics
Classifier: Topic :: Scientific/Engineering :: Visualization
Classifier: Topic :: Scientific/Engineering :: Information Analysis
Classifier: Topic :: Scientific/Engineering :: Mathematics
Requires-Python: >=3.8
License-File: LICENSE
Requires-Dist: requests
Requires-Dist: anesthetic
Provides-Extra: docs
Requires-Dist: sphinx; extra == "docs"
Requires-Dist: sphinx_rtd_theme; extra == "docs"
Requires-Dist: numpydoc; extra == "docs"
Provides-Extra: test
Requires-Dist: pytest; extra == "test"
Requires-Dist: pytest-cov; extra == "test"
Requires-Dist: flake8; extra == "test"
Requires-Dist: pydocstyle; extra == "test"
Requires-Dist: packaging; extra == "test"
Requires-Dist: pre-commit; extra == "test"
Requires-Dist: pytest-recording; extra == "test"
Dynamic: license-file
